{"stat.useItem.minecraft.iron_bars":2,"stat.craftItem.minecraft.leather_leggings":3,"stat.useItem.minecraft.command_block":3,"stat.useItem.minecraft.bow":14,"stat.walkOneCm":409412,"stat.playerKills":8,"stat.useItem.minecraft.stone":23,"stat.leaveGame":63,"stat.craftItem.minecraft.leather_boots":5,"stat.useItem.minecraft.skull":1,"stat.useItem.minecraft.carpet":1,"stat.useItem.minecraft.diamond_sword":5,"stat.useItem.minecraft.bedrock":1,"stat.jump":958,"stat.fallOneCm":20012,"stat.climbOneCm":74,"stat.crouchOneCm":14881,"stat.enderchestOpened":9,"stat.useItem.minecraft.obsidian":12,"stat.sprintOneCm":130179,"achievement.exploreAllBiomes":{"value":0,"progress":["Birch Forest Hills","Roofed Forest","Birch Forest","Extreme Hills+","Jungle","River","Forest","Plains","Extreme Hills","The End","Savanna"]},"stat.craftingTableInteraction":1,"achievement.openInventory":160,"stat.useItem.minecraft.iron_sword":28,"stat.useItem.minecraft.barrier":41,"stat.useItem.minecraft.flint_and_steel":7,"stat.damageTaken":33592,"stat.useItem.minecraft.wooden_button":4,"stat.killEntity.Enderman":5,"stat.mobKills":8,"stat.flyOneCm":1110419,"stat.deaths":12,"stat.useItem.minecraft.cobblestone_wall":19,"stat.drop":2,"stat.playOneMinute":404406,"stat.useItem.minecraft.wooden_sword":10,"stat.damageDealt":3675,"stat.useItem.minecraft.wool":19,"stat.killEntity.Zombie":3,"stat.timeSinceDeath":114183,"stat.useItem.minecraft.sign":4,"stat.useItem.minecraft.crafting_table":1}